{"name": "line", "subject": 95, "date": null, "paths": {"Finger": {"strokes": [{"x": 54, "y": 57, "z": null, "alpha": null, "beta": null, "gamma": null, "t": 1302553913999, "stroke_id": 0}, {"x": 55, "y": 57, "z": null, "alpha": null, "beta": null, "gamma": null, "t": 1302553914004, "stroke_id": 0}, {"x": 57, "y": 57, "z": null, "alpha": null, "beta": null, "gamma": null, "t": 1302553914009, "stroke_id": 0}, {"x": 58, "y": 57, "z": null, "alpha": null, "beta": null, "gamma": null, "t": 1302553914014, "stroke_id": 0}, {"x": 59, "y": 57, "z": null, "alpha": null, "beta": null, "gamma": null, "t": 1302553914019, "stroke_id": 0}, {"x": 61, "y": 58, "z": null, "alpha": null, "beta": null, "gamma": null, "t": 1302553914024, "stroke_id": 0}, {"x": 62, "y": 58, "z": null, "alpha": null, "beta": null, "gamma": null, "t": 1302553914029, "stroke_id": 0}, {"x": 63, "y": 58, "z": null, "alpha": null, "beta": null, "gamma": null, "t": 1302553914034, "stroke_id": 0}, {"x": 64, "y": 58, "z": null, "alpha": null, "beta": null, "gamma": null, "t": 1302553914039, "stroke_id": 0}, {"x": 65, "y": 58, "z": null, "alpha": null, "beta": null, "gamma": null, "t": 1302553914044, "stroke_id": 0}, {"x": 66, "y": 58, "z": null, "alpha": null, "beta": null, "gamma": null, "t": 1302553914049, "stroke_id": 0}, {"x": 67, "y": 59, "z": null, "alpha": null, "beta": null, "gamma": null, "t": 1302553914054, "stroke_id": 0}, {"x": 68, "y": 59, "z": null, "alpha": null, "beta": null, "gamma": null, "t": 1302553914059, "stroke_id": 0}, {"x": 70, "y": 59, "z": null, "alpha": null, "beta": null, "gamma": null, "t": 1302553914064, "stroke_id": 0}, {"x": 72, "y": 60, "z": null, "alpha": null, "beta": null, "gamma": null, "t": 1302553914070, "stroke_id": 0}, {"x": 74, "y": 60, "z": null, "alpha": null, "beta": null, "gamma": null, "t": 1302553914075, "stroke_id": 0}, {"x": 76, "y": 60, "z": null, "alpha": null, "beta": null, "gamma": null, "t": 1302553914080, "stroke_id": 0}, {"x": 78, "y": 61, "z": null, "alpha": null, "beta": null, "gamma": null, "t": 1302553914085, "stroke_id": 0}, {"x": 80, "y": 61, "z": null, "alpha": null, "beta": null, "gamma": null, "t": 1302553914090, "stroke_id": 0}, {"x": 83, "y": 62, "z": null, "alpha": null, "beta": null, "gamma": null, "t": 1302553914095, "stroke_id": 0}, {"x": 85, "y": 62, "z": null, "alpha": null, "beta": null, "gamma": null, "t": 1302553914100, "stroke_id": 0}, {"x": 88, "y": 63, "z": null, "alpha": null, "beta": null, "gamma": null, "t": 1302553914105, "stroke_id": 0}, {"x": 90, "y": 63, "z": null, "alpha": null, "beta": null, "gamma": null, "t": 1302553914110, "stroke_id": 0}, {"x": 93, "y": 64, "z": null, "alpha": null, "beta": null, "gamma": null, "t": 1302553914115, "stroke_id": 0}, {"x": 96, "y": 64, "z": null, "alpha": null, "beta": null, "gamma": null, "t": 1302553914120, "stroke_id": 0}, {"x": 98, "y": 65, "z": null, "alpha": null, "beta": null, "gamma": null, "t": 1302553914125, "stroke_id": 0}, {"x": 101, "y": 65, "z": null, "alpha": null, "beta": null, "gamma": null, "t": 1302553914130, "stroke_id": 0}, {"x": 103, "y": 66, "z": null, "alpha": null, "beta": null, "gamma": null, "t": 1302553914136, "stroke_id": 0}, {"x": 106, "y": 66, "z": null, "alpha": null, "beta": null, "gamma": null, "t": 1302553914141, "stroke_id": 0}, {"x": 108, "y": 67, "z": null, "alpha": null, "beta": null, "gamma": null, "t": 1302553914146, "stroke_id": 0}, {"x": 111, "y": 67, "z": null, "alpha": null, "beta": null, "gamma": null, "t": 1302553914151, "stroke_id": 0}, {"x": 113, "y": 67, "z": null, "alpha": null, "beta": null, "gamma": null, "t": 1302553914156, "stroke_id": 0}, {"x": 116, "y": 68, "z": null, "alpha": null, "beta": null, "gamma": null, "t": 1302553914161, "stroke_id": 0}, {"x": 118, "y": 68, "z": null, "alpha": null, "beta": null, "gamma": null, "t": 1302553914166, "stroke_id": 0}, {"x": 120, "y": 68, "z": null, "alpha": null, "beta": null, "gamma": null, "t": 1302553914171, "stroke_id": 0}, {"x": 122, "y": 69, "z": null, "alpha": null, "beta": null, "gamma": null, "t": 1302553914176, "stroke_id": 0}, {"x": 124, "y": 69, "z": null, "alpha": null, "beta": null, "gamma": null, "t": 1302553914181, "stroke_id": 0}, {"x": 127, "y": 69, "z": null, "alpha": null, "beta": null, "gamma": null, "t": 1302553914186, "stroke_id": 0}, {"x": 128, "y": 70, "z": null, "alpha": null, "beta": null, "gamma": null, "t": 1302553914191, "stroke_id": 0}, {"x": 130, "y": 70, "z": null, "alpha": null, "beta": null, "gamma": null, "t": 1302553914196, "stroke_id": 0}, {"x": 132, "y": 70, "z": null, "alpha": null, "beta": null, "gamma": null, "t": 1302553914202, "stroke_id": 0}, {"x": 134, "y": 70, "z": null, "alpha": null, "beta": null, "gamma": null, "t": 1302553914207, "stroke_id": 0}, {"x": 136, "y": 70, "z": null, "alpha": null, "beta": null, "gamma": null, "t": 1302553914212, "stroke_id": 0}, {"x": 137, "y": 71, "z": null, "alpha": null, "beta": null, "gamma": null, "t": 1302553914217, "stroke_id": 0}, {"x": 139, "y": 71, "z": null, "alpha": null, "beta": null, "gamma": null, "t": 1302553914222, "stroke_id": 0}, {"x": 140, "y": 71, "z": null, "alpha": null, "beta": null, "gamma": null, "t": 1302553914227, "stroke_id": 0}, {"x": 142, "y": 71, "z": null, "alpha": null, "beta": null, "gamma": null, "t": 1302553914232, "stroke_id": 0}, {"x": 143, "y": 71, "z": null, "alpha": null, "beta": null, "gamma": null, "t": 1302553914237, "stroke_id": 0}, {"x": 145, "y": 71, "z": null, "alpha": null, "beta": null, "gamma": null, "t": 1302553914242, "stroke_id": 0}, {"x": 146, "y": 71, "z": null, "alpha": null, "beta": null, "gamma": null, "t": 1302553914247, "stroke_id": 0}, {"x": 148, "y": 72, "z": null, "alpha": null, "beta": null, "gamma": null, "t": 1302553914252, "stroke_id": 0}, {"x": 149, "y": 72, "z": null, "alpha": null, "beta": null, "gamma": null, "t": 1302553914257, "stroke_id": 0}, {"x": 150, "y": 72, "z": null, "alpha": null, "beta": null, "gamma": null, "t": 1302553914262, "stroke_id": 0}, {"x": 151, "y": 72, "z": null, "alpha": null, "beta": null, "gamma": null, "t": 1302553914267, "stroke_id": 0}, {"x": 152, "y": 72, "z": null, "alpha": null, "beta": null, "gamma": null, "t": 1302553914273, "stroke_id": 0}, {"x": 153, "y": 73, "z": null, "alpha": null, "beta": null, "gamma": null, "t": 1302553914278, "stroke_id": 0}, {"x": 154, "y": 72, "z": null, "alpha": null, "beta": null, "gamma": null, "t": 1302553914283, "stroke_id": 0}, {"x": 155, "y": 72, "z": null, "alpha": null, "beta": null, "gamma": null, "t": 1302553914288, "stroke_id": 0}, {"x": 156, "y": 72, "z": null, "alpha": null, "beta": null, "gamma": null, "t": 1302553914293, "stroke_id": 0}, {"x": 157, "y": 72, "z": null, "alpha": null, "beta": null, "gamma": null, "t": 1302553914298, "stroke_id": 0}, {"x": 160, "y": 72, "z": null, "alpha": null, "beta": null, "gamma": null, "t": 1302553914303, "stroke_id": 0}, {"x": 162, "y": 73, "z": null, "alpha": null, "beta": null, "gamma": null, "t": 1302553914308, "stroke_id": 0}, {"x": 162, "y": 74, "z": null, "alpha": null, "beta": null, "gamma": null, "t": 1302553914313, "stroke_id": 0}, {"x": 163, "y": 74, "z": null, "alpha": null, "beta": null, "gamma": null, "t": 1302553914318, "stroke_id": 0}, {"x": 164, "y": 74, "z": null, "alpha": null, "beta": null, "gamma": null, "t": 1302553914323, "stroke_id": 0}, {"x": 165, "y": 74, "z": null, "alpha": null, "beta": null, "gamma": null, "t": 1302553914328, "stroke_id": 0}, {"x": 166, "y": 74, "z": null, "alpha": null, "beta": null, "gamma": null, "t": 1302553914333, "stroke_id": 0}, {"x": 168, "y": 74, "z": null, "alpha": null, "beta": null, "gamma": null, "t": 1302553914339, "stroke_id": 0}, {"x": 169, "y": 75, "z": null, "alpha": null, "beta": null, "gamma": null, "t": 1302553914344, "stroke_id": 0}, {"x": 169, "y": 75, "z": null, "alpha": null, "beta": null, "gamma": null, "t": 1302553914349, "stroke_id": 0}, {"x": 170, "y": 76, "z": null, "alpha": null, "beta": null, "gamma": null, "t": 1302553914354, "stroke_id": 0}, {"x": 170, "y": 76, "z": null, "alpha": null, "beta": null, "gamma": null, "t": 1302553914359, "stroke_id": 0}, {"x": 171, "y": 77, "z": null, "alpha": null, "beta": null, "gamma": null, "t": 1302553914364, "stroke_id": 0}, {"x": 171, "y": 77, "z": null, "alpha": null, "beta": null, "gamma": null, "t": 1302553914369, "stroke_id": 0}, {"x": 170, "y": 77, "z": null, "alpha": null, "beta": null, "gamma": null, "t": 1302553914374, "stroke_id": 0}, {"x": 170, "y": 77, "z": null, "alpha": null, "beta": null, "gamma": null, "t": 1302553914379, "stroke_id": 0}, {"x": 171, "y": 76, "z": null, "alpha": null, "beta": null, "gamma": null, "t": 1302553914384, "stroke_id": 0}, {"x": 171, "y": 76, "z": null, "alpha": null, "beta": null, "gamma": null, "t": 1302553914389, "stroke_id": 0}, {"x": 171, "y": 76, "z": null, "alpha": null, "beta": null, "gamma": null, "t": 1302553914394, "stroke_id": 0}, {"x": 171, "y": 76, "z": null, "alpha": null, "beta": null, "gamma": null, "t": 1302553914399, "stroke_id": 0}, {"x": 172, "y": 76, "z": null, "alpha": null, "beta": null, "gamma": null, "t": 1302553914405, "stroke_id": 0}]}}, "device": {"mouse": false, "pen": false, "finger": true, "acceleration": false, "webcam": false}}