{"name": "line", "subject": 95, "date": null, "paths": {"Finger": {"strokes": [{"x": 54, "y": 57, "z": null, "alpha": null, "beta": null, "gamma": null, "t": 1302553913999, "stroke_id": 0}, {"x": 57, "y": 57, "z": null, "alpha": null, "beta": null, "gamma": null, "t": 1302553914004, "stroke_id": 0}, {"x": 59, "y": 57, "z": null, "alpha": null, "beta": null, "gamma": null, "t": 1302553914009, "stroke_id": 0}, {"x": 61, "y": 56, "z": null, "alpha": null, "beta": null, "gamma": null, "t": 1302553914014, "stroke_id": 0}, {"x": 63, "y": 56, "z": null, "alpha": null, "beta": null, "gamma": null, "t": 1302553914019, "stroke_id": 0}, {"x": 65, "y": 56, "z": null, "alpha": null, "beta": null, "gamma": null, "t": 1302553914024, "stroke_id": 0}, {"x": 66, "y": 56, "z": null, "alpha": null, "beta": null, "gamma": null, "t": 1302553914029, "stroke_id": 0}, {"x": 67, "y": 56, "z": null, "alpha": null, "beta": null, "gamma": null, "t": 1302553914034, "stroke_id": 0}, {"x": 69, "y": 56, "z": null, "alpha": null, "beta": null, "gamma": null, "t": 1302553914039, "stroke_id": 0}, {"x": 70, "y": 56, "z": null, "alpha": null, "beta": null, "gamma": null, "t": 1302553914044, "stroke_id": 0}, {"x": 70, "y": 56, "z": null, "alpha": null, "beta": null, "gamma": null, "t": 1302553914049, "stroke_id": 0}, {"x": 71, "y": 56, "z": null, "alpha": null, "beta": null, "gamma": null, "t": 1302553914054, "stroke_id": 0}, {"x": 72, "y": 56, "z": null, "alpha": null, "beta": null, "gamma": null, "t": 1302553914059, "stroke_id": 0}, {"x": 73, "y": 55, "z": null, "alpha": null, "beta": null, "gamma": null, "t": 1302553914064, "stroke_id": 0}, {"x": 74, "y": 55, "z": null, "alpha": null, "beta": null, "gamma": null, "t": 1302553914070, "stroke_id": 0}, {"x": 76, "y": 55, "z": null, "alpha": null, "beta": null, "gamma": null, "t": 1302553914075, "stroke_id": 0}, {"x": 77, "y": 55, "z": null, "alpha": null, "beta": null, "gamma": null, "t": 1302553914080, "stroke_id": 0}, {"x": 79, "y": 55, "z": null, "alpha": null, "beta": null, "gamma": null, "t": 1302553914085, "stroke_id": 0}, {"x": 80, "y": 55, "z": null, "alpha": null, "beta": null, "gamma": null, "t": 1302553914090, "stroke_id": 0}, {"x": 82, "y": 55, "z": null, "alpha": null, "beta": null, "gamma": null, "t": 1302553914095, "stroke_id": 0}, {"x": 84, "y": 55, "z": null, "alpha": null, "beta": null, "gamma": null, "t": 1302553914100, "stroke_id": 0}, {"x": 87, "y": 55, "z": null, "alpha": null, "beta": null, "gamma": null, "t": 1302553914105, "stroke_id": 0}, {"x": 89, "y": 55, "z": null, "alpha": null, "beta": null, "gamma": null, "t": 1302553914110, "stroke_id": 0}, {"x": 91, "y": 55, "z": null, "alpha": null, "beta": null, "gamma": null, "t": 1302553914115, "stroke_id": 0}, {"x": 94, "y": 55, "z": null, "alpha": null, "beta": null, "gamma": null, "t": 1302553914120, "stroke_id": 0}, {"x": 97, "y": 54, "z": null, "alpha": null, "beta": null, "gamma": null, "t": 1302553914125, "stroke_id": 0}, {"x": 99, "y": 54, "z": null, "alpha": null, "beta": null, "gamma": null, "t": 1302553914130, "stroke_id": 0}, {"x": 102, "y": 54, "z": null, "alpha": null, "beta": null, "gamma": null, "t": 1302553914136, "stroke_id": 0}, {"x": 104, "y": 54, "z": null, "alpha": null, "beta": null, "gamma": null, "t": 1302553914141, "stroke_id": 0}, {"x": 107, "y": 54, "z": null, "alpha": null, "beta": null, "gamma": null, "t": 1302553914146, "stroke_id": 0}, {"x": 110, "y": 54, "z": null, "alpha": null, "beta": null, "gamma": null, "t": 1302553914151, "stroke_id": 0}, {"x": 112, "y": 53, "z": null, "alpha": null, "beta": null, "gamma": null, "t": 1302553914156, "stroke_id": 0}, {"x": 115, "y": 53, "z": null, "alpha": null, "beta": null, "gamma": null, "t": 1302553914161, "stroke_id": 0}, {"x": 117, "y": 53, "z": null, "alpha": null, "beta": null, "gamma": null, "t": 1302553914166, "stroke_id": 0}, {"x": 120, "y": 53, "z": null, "alpha": null, "beta": null, "gamma": null, "t": 1302553914171, "stroke_id": 0}, {"x": 122, "y": 53, "z": null, "alpha": null, "beta": null, "gamma": null, "t": 1302553914176, "stroke_id": 0}, {"x": 124, "y": 52, "z": null, "alpha": null, "beta": null, "gamma": null, "t": 1302553914181, "stroke_id": 0}, {"x": 126, "y": 52, "z": null, "alpha": null, "beta": null, "gamma": null, "t": 1302553914186, "stroke_id": 0}, {"x": 129, "y": 52, "z": null, "alpha": null, "beta": null, "gamma": null, "t": 1302553914191, "stroke_id": 0}, {"x": 131, "y": 52, "z": null, "alpha": null, "beta": null, "gamma": null, "t": 1302553914196, "stroke_id": 0}, {"x": 133, "y": 51, "z": null, "alpha": null, "beta": null, "gamma": null, "t": 1302553914202, "stroke_id": 0}, {"x": 135, "y": 51, "z": null, "alpha": null, "beta": null, "gamma": null, "t": 1302553914207, "stroke_id": 0}, {"x": 137, "y": 51, "z": null, "alpha": null, "beta": null, "gamma": null, "t": 1302553914212, "stroke_id": 0}, {"x": 138, "y": 51, "z": null, "alpha": null, "beta": null, "gamma": null, "t": 1302553914217, "stroke_id": 0}, {"x": 140, "y": 51, "z": null, "alpha": null, "beta": null, "gamma": null, "t": 1302553914222, "stroke_id": 0}, {"x": 142, "y": 50, "z": null, "alpha": null, "beta": null, "gamma": null, "t": 1302553914227, "stroke_id": 0}, {"x": 143, "y": 50, "z": null, "alpha": null, "beta": null, "gamma": null, "t": 1302553914232, "stroke_id": 0}, {"x": 145, "y": 50, "z": null, "alpha": null, "beta": null, "gamma": null, "t": 1302553914237, "stroke_id": 0}, {"x": 146, "y": 50, "z": null, "alpha": null, "beta": null, "gamma": null, "t": 1302553914242, "stroke_id": 0}, {"x": 148, "y": 49, "z": null, "alpha": null, "beta": null, "gamma": null, "t": 1302553914247, "stroke_id": 0}, {"x": 149, "y": 49, "z": null, "alpha": null, "beta": null, "gamma": null, "t": 1302553914252, "stroke_id": 0}, {"x": 151, "y": 49, "z": null, "alpha": null, "beta": null, "gamma": null, "t": 1302553914257, "stroke_id": 0}, {"x": 152, "y": 49, "z": null, "alpha": null, "beta": null, "gamma": null, "t": 1302553914262, "stroke_id": 0}, {"x": 153, "y": 49, "z": null, "alpha": null, "beta": null, "gamma": null, "t": 1302553914267, "stroke_id": 0}, {"x": 154, "y": 48, "z": null, "alpha": null, "beta": null, "gamma": null, "t": 1302553914273, "stroke_id": 0}, {"x": 155, "y": 48, "z": null, "alpha": null, "beta": null, "gamma": null, "t": 1302553914278, "stroke_id": 0}, {"x": 156, "y": 48, "z": null, "alpha": null, "beta": null, "gamma": null, "t": 1302553914283, "stroke_id": 0}, {"x": 158, "y": 48, "z": null, "alpha": null, "beta": null, "gamma": null, "t": 1302553914288, "stroke_id": 0}, {"x": 159, "y": 47, "z": null, "alpha": null, "beta": null, "gamma": null, "t": 1302553914293, "stroke_id": 0}, {"x": 160, "y": 47, "z": null, "alpha": null, "beta": null, "gamma": null, "t": 1302553914298, "stroke_id": 0}, {"x": 161, "y": 46, "z": null, "alpha": null, "beta": null, "gamma": null, "t": 1302553914303, "stroke_id": 0}, {"x": 162, "y": 46, "z": null, "alpha": null, "beta": null, "gamma": null, "t": 1302553914308, "stroke_id": 0}, {"x": 164, "y": 45, "z": null, "alpha": null, "beta": null, "gamma": null, "t": 1302553914313, "stroke_id": 0}, {"x": 165, "y": 46, "z": null, "alpha": null, "beta": null, "gamma": null, "t": 1302553914318, "stroke_id": 0}, {"x": 167, "y": 46, "z": null, "alpha": null, "beta": null, "gamma": null, "t": 1302553914323, "stroke_id": 0}, {"x": 168, "y": 46, "z": null, "alpha": null, "beta": null, "gamma": null, "t": 1302553914328, "stroke_id": 0}, {"x": 170, "y": 46, "z": null, "alpha": null, "beta": null, "gamma": null, "t": 1302553914333, "stroke_id": 0}, {"x": 171, "y": 47, "z": null, "alpha": null, "beta": null, "gamma": null, "t": 1302553914339, "stroke_id": 0}, {"x": 172, "y": 48, "z": null, "alpha": null, "beta": null, "gamma": null, "t": 1302553914344, "stroke_id": 0}, {"x": 173, "y": 49, "z": null, "alpha": null, "beta": null, "gamma": null, "t": 1302553914349, "stroke_id": 0}, {"x": 173, "y": 49, "z": null, "alpha": null, "beta": null, "gamma": null, "t": 1302553914354, "stroke_id": 0}, {"x": 173, "y": 49, "z": null, "alpha": null, "beta": null, "gamma": null, "t": 1302553914359, "stroke_id": 0}, {"x": 173, "y": 49, "z": null, "alpha": null, "beta": null, "gamma": null, "t": 1302553914364, "stroke_id": 0}, {"x": 173, "y": 49, "z": null, "alpha": null, "beta": null, "gamma": null, "t": 1302553914369, "stroke_id": 0}, {"x": 173, "y": 49, "z": null, "alpha": null, "beta": null, "gamma": null, "t": 1302553914374, "stroke_id": 0}, {"x": 173, "y": 48, "z": null, "alpha": null, "beta": null, "gamma": null, "t": 1302553914379, "stroke_id": 0}, {"x": 174, "y": 48, "z": null, "alpha": null, "beta": null, "gamma": null, "t": 1302553914384, "stroke_id": 0}, {"x": 175, "y": 48, "z": null, "alpha": null, "beta": null, "gamma": null, "t": 1302553914389, "stroke_id": 0}, {"x": 175, "y": 48, "z": null, "alpha": null, "beta": null, "gamma": null, "t": 1302553914394, "stroke_id": 0}, {"x": 175, "y": 49, "z": null, "alpha": null, "beta": null, "gamma": null, "t": 1302553914399, "stroke_id": 0}, {"x": 174, "y": 49, "z": null, "alpha": null, "beta": null, "gamma": null, "t": 1302553914405, "stroke_id": 0}]}}, "device": {"mouse": false, "pen": false, "finger": true, "acceleration": false, "webcam": false}}