{"name": "pitchfork", "subject": 68, "date": null, "paths": {"Finger": {"strokes": [{"x": 74, "y": 23, "z": null, "alpha": null, "beta": null, "gamma": null, "t": 1302291323117, "stroke_id": 0}, {"x": 74, "y": 25, "z": null, "alpha": null, "beta": null, "gamma": null, "t": 1302291323122, "stroke_id": 0}, {"x": 74, "y": 28, "z": null, "alpha": null, "beta": null, "gamma": null, "t": 1302291323127, "stroke_id": 0}, {"x": 74, "y": 32, "z": null, "alpha": null, "beta": null, "gamma": null, "t": 1302291323132, "stroke_id": 0}, {"x": 75, "y": 35, "z": null, "alpha": null, "beta": null, "gamma": null, "t": 1302291323137, "stroke_id": 0}, {"x": 76, "y": 39, "z": null, "alpha": null, "beta": null, "gamma": null, "t": 1302291323142, "stroke_id": 0}, {"x": 77, "y": 42, "z": null, "alpha": null, "beta": null, "gamma": null, "t": 1302291323147, "stroke_id": 0}, {"x": 79, "y": 44, "z": null, "alpha": null, "beta": null, "gamma": null, "t": 1302291323152, "stroke_id": 0}, {"x": 80, "y": 46, "z": null, "alpha": null, "beta": null, "gamma": null, "t": 1302291323157, "stroke_id": 0}, {"x": 81, "y": 48, "z": null, "alpha": null, "beta": null, "gamma": null, "t": 1302291323162, "stroke_id": 0}, {"x": 83, "y": 49, "z": null, "alpha": null, "beta": null, "gamma": null, "t": 1302291323167, "stroke_id": 0}, {"x": 84, "y": 50, "z": null, "alpha": null, "beta": null, "gamma": null, "t": 1302291323172, "stroke_id": 0}, {"x": 84, "y": 51, "z": null, "alpha": null, "beta": null, "gamma": null, "t": 1302291323177, "stroke_id": 0}, {"x": 85, "y": 52, "z": null, "alpha": null, "beta": null, "gamma": null, "t": 1302291323182, "stroke_id": 0}, {"x": 86, "y": 52, "z": null, "alpha": null, "beta": null, "gamma": null, "t": 1302291323187, "stroke_id": 0}, {"x": 87, "y": 53, "z": null, "alpha": null, "beta": null, "gamma": null, "t": 1302291323192, "stroke_id": 0}, {"x": 88, "y": 54, "z": null, "alpha": null, "beta": null, "gamma": null, "t": 1302291323198, "stroke_id": 0}, {"x": 90, "y": 55, "z": null, "alpha": null, "beta": null, "gamma": null, "t": 1302291323203, "stroke_id": 0}, {"x": 92, "y": 57, "z": null, "alpha": null, "beta": null, "gamma": null, "t": 1302291323208, "stroke_id": 0}, {"x": 96, "y": 59, "z": null, "alpha": null, "beta": null, "gamma": null, "t": 1302291323213, "stroke_id": 0}, {"x": 100, "y": 60, "z": null, "alpha": null, "beta": null, "gamma": null, "t": 1302291323218, "stroke_id": 0}, {"x": 104, "y": 60, "z": null, "alpha": null, "beta": null, "gamma": null, "t": 1302291323223, "stroke_id": 0}, {"x": 108, "y": 60, "z": null, "alpha": null, "beta": null, "gamma": null, "t": 1302291323228, "stroke_id": 0}, {"x": 111, "y": 59, "z": null, "alpha": null, "beta": null, "gamma": null, "t": 1302291323233, "stroke_id": 0}, {"x": 113, "y": 59, "z": null, "alpha": null, "beta": null, "gamma": null, "t": 1302291323238, "stroke_id": 0}, {"x": 115, "y": 58, "z": null, "alpha": null, "beta": null, "gamma": null, "t": 1302291323243, "stroke_id": 0}, {"x": 116, "y": 57, "z": null, "alpha": null, "beta": null, "gamma": null, "t": 1302291323248, "stroke_id": 0}, {"x": 117, "y": 56, "z": null, "alpha": null, "beta": null, "gamma": null, "t": 1302291323253, "stroke_id": 0}, {"x": 117, "y": 56, "z": null, "alpha": null, "beta": null, "gamma": null, "t": 1302291323258, "stroke_id": 0}, {"x": 118, "y": 55, "z": null, "alpha": null, "beta": null, "gamma": null, "t": 1302291323263, "stroke_id": 0}, {"x": 118, "y": 54, "z": null, "alpha": null, "beta": null, "gamma": null, "t": 1302291323268, "stroke_id": 0}, {"x": 118, "y": 54, "z": null, "alpha": null, "beta": null, "gamma": null, "t": 1302291323274, "stroke_id": 0}, {"x": 118, "y": 53, "z": null, "alpha": null, "beta": null, "gamma": null, "t": 1302291323279, "stroke_id": 0}, {"x": 119, "y": 52, "z": null, "alpha": null, "beta": null, "gamma": null, "t": 1302291323284, "stroke_id": 0}, {"x": 119, "y": 51, "z": null, "alpha": null, "beta": null, "gamma": null, "t": 1302291323289, "stroke_id": 0}, {"x": 119, "y": 50, "z": null, "alpha": null, "beta": null, "gamma": null, "t": 1302291323294, "stroke_id": 0}, {"x": 119, "y": 49, "z": null, "alpha": null, "beta": null, "gamma": null, "t": 1302291323299, "stroke_id": 0}, {"x": 119, "y": 47, "z": null, "alpha": null, "beta": null, "gamma": null, "t": 1302291323304, "stroke_id": 0}, {"x": 119, "y": 46, "z": null, "alpha": null, "beta": null, "gamma": null, "t": 1302291323309, "stroke_id": 0}, {"x": 119, "y": 45, "z": null, "alpha": null, "beta": null, "gamma": null, "t": 1302291323314, "stroke_id": 0}, {"x": 120, "y": 43, "z": null, "alpha": null, "beta": null, "gamma": null, "t": 1302291323319, "stroke_id": 0}, {"x": 120, "y": 42, "z": null, "alpha": null, "beta": null, "gamma": null, "t": 1302291323324, "stroke_id": 0}, {"x": 120, "y": 41, "z": null, "alpha": null, "beta": null, "gamma": null, "t": 1302291323329, "stroke_id": 0}, {"x": 120, "y": 39, "z": null, "alpha": null, "beta": null, "gamma": null, "t": 1302291323334, "stroke_id": 0}, {"x": 120, "y": 38, "z": null, "alpha": null, "beta": null, "gamma": null, "t": 1302291323339, "stroke_id": 0}, {"x": 120, "y": 37, "z": null, "alpha": null, "beta": null, "gamma": null, "t": 1302291323344, "stroke_id": 0}, {"x": 120, "y": 35, "z": null, "alpha": null, "beta": null, "gamma": null, "t": 1302291323349, "stroke_id": 0}, {"x": 120, "y": 34, "z": null, "alpha": null, "beta": null, "gamma": null, "t": 1302291323355, "stroke_id": 0}, {"x": 120, "y": 33, "z": null, "alpha": null, "beta": null, "gamma": null, "t": 1302291323360, "stroke_id": 0}, {"x": 120, "y": 32, "z": null, "alpha": null, "beta": null, "gamma": null, "t": 1302291323365, "stroke_id": 0}, {"x": 120, "y": 30, "z": null, "alpha": null, "beta": null, "gamma": null, "t": 1302291323370, "stroke_id": 0}, {"x": 120, "y": 29, "z": null, "alpha": null, "beta": null, "gamma": null, "t": 1302291323375, "stroke_id": 0}, {"x": 120, "y": 28, "z": null, "alpha": null, "beta": null, "gamma": null, "t": 1302291323380, "stroke_id": 0}, {"x": 120, "y": 27, "z": null, "alpha": null, "beta": null, "gamma": null, "t": 1302291323385, "stroke_id": 0}, {"x": 119, "y": 26, "z": null, "alpha": null, "beta": null, "gamma": null, "t": 1302291323390, "stroke_id": 0}, {"x": 119, "y": 25, "z": null, "alpha": null, "beta": null, "gamma": null, "t": 1302291323395, "stroke_id": 0}, {"x": 119, "y": 23, "z": null, "alpha": null, "beta": null, "gamma": null, "t": 1302291323400, "stroke_id": 0}, {"x": 119, "y": 22, "z": null, "alpha": null, "beta": null, "gamma": null, "t": 1302291323405, "stroke_id": 0}, {"x": 118, "y": 20, "z": null, "alpha": null, "beta": null, "gamma": null, "t": 1302291323410, "stroke_id": 0}, {"x": 118, "y": 20, "z": null, "alpha": null, "beta": null, "gamma": null, "t": 1302291323415, "stroke_id": 0}, {"x": 118, "y": 18, "z": null, "alpha": null, "beta": null, "gamma": null, "t": 1302291323420, "stroke_id": 0}, {"x": 117, "y": 17, "z": null, "alpha": null, "beta": null, "gamma": null, "t": 1302291323425, "stroke_id": 0}, {"x": 117, "y": 16, "z": null, "alpha": null, "beta": null, "gamma": null, "t": 1302291323431, "stroke_id": 0}, {"x": 117, "y": 15, "z": null, "alpha": null, "beta": null, "gamma": null, "t": 1302291323436, "stroke_id": 0}, {"x": 117, "y": 14, "z": null, "alpha": null, "beta": null, "gamma": null, "t": 1302291323441, "stroke_id": 0}, {"x": 116, "y": 13, "z": null, "alpha": null, "beta": null, "gamma": null, "t": 1302291323446, "stroke_id": 0}, {"x": 116, "y": 12, "z": null, "alpha": null, "beta": null, "gamma": null, "t": 1302291323451, "stroke_id": 0}, {"x": 116, "y": 12, "z": null, "alpha": null, "beta": null, "gamma": null, "t": 1302291323456, "stroke_id": 0}, {"x": 116, "y": 11, "z": null, "alpha": null, "beta": null, "gamma": null, "t": 1302291323461, "stroke_id": 0}, {"x": 116, "y": 11, "z": null, "alpha": null, "beta": null, "gamma": null, "t": 1302291323466, "stroke_id": 0}, {"x": 115, "y": 10, "z": null, "alpha": null, "beta": null, "gamma": null, "t": 1302291323471, "stroke_id": 0}, {"x": 115, "y": 10, "z": null, "alpha": null, "beta": null, "gamma": null, "t": 1302291323476, "stroke_id": 0}, {"x": 115, "y": 9, "z": null, "alpha": null, "beta": null, "gamma": null, "t": 1302291323481, "stroke_id": 0}, {"x": 115, "y": 9, "z": null, "alpha": null, "beta": null, "gamma": null, "t": 1302291323486, "stroke_id": 0}, {"x": 115, "y": 9, "z": null, "alpha": null, "beta": null, "gamma": null, "t": 1302291323491, "stroke_id": 0}, {"x": 115, "y": 8, "z": null, "alpha": null, "beta": null, "gamma": null, "t": 1302291323496, "stroke_id": 0}, {"x": 115, "y": 8, "z": null, "alpha": null, "beta": null, "gamma": null, "t": 1302291323501, "stroke_id": 0}, {"x": 114, "y": 7, "z": null, "alpha": null, "beta": null, "gamma": null, "t": 1302291323507, "stroke_id": 0}, {"x": 94, "y": 14, "z": null, "alpha": null, "beta": null, "gamma": null, "t": 1302291324022, "stroke_id": 1}, {"x": 96, "y": 19, "z": null, "alpha": null, "beta": null, "gamma": null, "t": 1302291324027, "stroke_id": 1}, {"x": 97, "y": 24, "z": null, "alpha": null, "beta": null, "gamma": null, "t": 1302291324032, "stroke_id": 1}, {"x": 99, "y": 29, "z": null, "alpha": null, "beta": null, "gamma": null, "t": 1302291324037, "stroke_id": 1}, {"x": 101, "y": 34, "z": null, "alpha": null, "beta": null, "gamma": null, "t": 1302291324042, "stroke_id": 1}, {"x": 103, "y": 39, "z": null, "alpha": null, "beta": null, "gamma": null, "t": 1302291324048, "stroke_id": 1}, {"x": 105, "y": 43, "z": null, "alpha": null, "beta": null, "gamma": null, "t": 1302291324053, "stroke_id": 1}, {"x": 107, "y": 47, "z": null, "alpha": null, "beta": null, "gamma": null, "t": 1302291324058, "stroke_id": 1}, {"x": 108, "y": 51, "z": null, "alpha": null, "beta": null, "gamma": null, "t": 1302291324063, "stroke_id": 1}, {"x": 110, "y": 54, "z": null, "alpha": null, "beta": null, "gamma": null, "t": 1302291324068, "stroke_id": 1}, {"x": 111, "y": 57, "z": null, "alpha": null, "beta": null, "gamma": null, "t": 1302291324074, "stroke_id": 1}, {"x": 111, "y": 59, "z": null, "alpha": null, "beta": null, "gamma": null, "t": 1302291324079, "stroke_id": 1}, {"x": 112, "y": 61, "z": null, "alpha": null, "beta": null, "gamma": null, "t": 1302291324084, "stroke_id": 1}, {"x": 113, "y": 62, "z": null, "alpha": null, "beta": null, "gamma": null, "t": 1302291324089, "stroke_id": 1}, {"x": 113, "y": 63, "z": null, "alpha": null, "beta": null, "gamma": null, "t": 1302291324094, "stroke_id": 1}, {"x": 114, "y": 65, "z": null, "alpha": null, "beta": null, "gamma": null, "t": 1302291324100, "stroke_id": 1}, {"x": 114, "y": 66, "z": null, "alpha": null, "beta": null, "gamma": null, "t": 1302291324105, "stroke_id": 1}, {"x": 115, "y": 67, "z": null, "alpha": null, "beta": null, "gamma": null, "t": 1302291324110, "stroke_id": 1}, {"x": 116, "y": 69, "z": null, "alpha": null, "beta": null, "gamma": null, "t": 1302291324115, "stroke_id": 1}, {"x": 116, "y": 71, "z": null, "alpha": null, "beta": null, "gamma": null, "t": 1302291324120, "stroke_id": 1}, {"x": 117, "y": 72, "z": null, "alpha": null, "beta": null, "gamma": null, "t": 1302291324126, "stroke_id": 1}, {"x": 118, "y": 74, "z": null, "alpha": null, "beta": null, "gamma": null, "t": 1302291324131, "stroke_id": 1}, {"x": 119, "y": 76, "z": null, "alpha": null, "beta": null, "gamma": null, "t": 1302291324136, "stroke_id": 1}, {"x": 120, "y": 77, "z": null, "alpha": null, "beta": null, "gamma": null, "t": 1302291324141, "stroke_id": 1}, {"x": 121, "y": 79, "z": null, "alpha": null, "beta": null, "gamma": null, "t": 1302291324146, "stroke_id": 1}, {"x": 121, "y": 81, "z": null, "alpha": null, "beta": null, "gamma": null, "t": 1302291324152, "stroke_id": 1}, {"x": 122, "y": 82, "z": null, "alpha": null, "beta": null, "gamma": null, "t": 1302291324157, "stroke_id": 1}, {"x": 123, "y": 84, "z": null, "alpha": null, "beta": null, "gamma": null, "t": 1302291324162, "stroke_id": 1}, {"x": 124, "y": 85, "z": null, "alpha": null, "beta": null, "gamma": null, "t": 1302291324167, "stroke_id": 1}, {"x": 125, "y": 87, "z": null, "alpha": null, "beta": null, "gamma": null, "t": 1302291324172, "stroke_id": 1}, {"x": 125, "y": 88, "z": null, "alpha": null, "beta": null, "gamma": null, "t": 1302291324178, "stroke_id": 1}, {"x": 126, "y": 89, "z": null, "alpha": null, "beta": null, "gamma": null, "t": 1302291324183, "stroke_id": 1}, {"x": 127, "y": 90, "z": null, "alpha": null, "beta": null, "gamma": null, "t": 1302291324188, "stroke_id": 1}, {"x": 127, "y": 91, "z": null, "alpha": null, "beta": null, "gamma": null, "t": 1302291324193, "stroke_id": 1}, {"x": 128, "y": 92, "z": null, "alpha": null, "beta": null, "gamma": null, "t": 1302291324198, "stroke_id": 1}, {"x": 128, "y": 93, "z": null, "alpha": null, "beta": null, "gamma": null, "t": 1302291324204, "stroke_id": 1}, {"x": 129, "y": 94, "z": null, "alpha": null, "beta": null, "gamma": null, "t": 1302291324209, "stroke_id": 1}, {"x": 129, "y": 95, "z": null, "alpha": null, "beta": null, "gamma": null, "t": 1302291324214, "stroke_id": 1}, {"x": 130, "y": 96, "z": null, "alpha": null, "beta": null, "gamma": null, "t": 1302291324219, "stroke_id": 1}, {"x": 130, "y": 96, "z": null, "alpha": null, "beta": null, "gamma": null, "t": 1302291324225, "stroke_id": 1}]}}, "device": {"mouse": false, "pen": false, "finger": true, "acceleration": false, "webcam": false}}